ai_prishtina_vectordb/__init__.py
ai_prishtina_vectordb/analytics.py
ai_prishtina_vectordb/caching.py
ai_prishtina_vectordb/chroma_features.py
ai_prishtina_vectordb/collaboration.py
ai_prishtina_vectordb/config.py
ai_prishtina_vectordb/data_sources.py
ai_prishtina_vectordb/database.py
ai_prishtina_vectordb/distributed.py
ai_prishtina_vectordb/embeddings.py
ai_prishtina_vectordb/enterprise.py
ai_prishtina_vectordb/exceptions.py
ai_prishtina_vectordb/features.py
ai_prishtina_vectordb/logger.py
ai_prishtina_vectordb/metrics.py
ai_prishtina_vectordb/multimodal_search.py
ai_prishtina_vectordb/multitenancy.py
ai_prishtina_vectordb/performance.py
ai_prishtina_vectordb/query_language.py
ai_prishtina_vectordb/security.py
ai_prishtina_vectordb/validation.py
ai_prishtina_vectordb/vectorizer.py
ai_prishtina_vectordb/api/__init__.py
ai_prishtina_vectordb/api/client.py
ai_prishtina_vectordb/api/exceptions.py
ai_prishtina_vectordb/api/features.py
ai_prishtina_vectordb/config/config_manager.py
ai_prishtina_vectordb/config/docker_manager.py
ai_prishtina_vectordb/tests/conftest.py
ai_prishtina_vectordb/tests/test_chroma_features.py
ai_prishtina_vectordb-1.0.1.dist-info/licenses/LICENSE
ai_prishtina_vectordb-1.0.1.dist-info/METADATA
ai_prishtina_vectordb-1.0.1.dist-info/WHEEL
ai_prishtina_vectordb-1.0.1.dist-info/top_level.txt
ai_prishtina_vectordb-1.0.1.dist-info/RECORD
