Metadata-Version: 2.4
Name: ai-prishtina-vectordb
Version: 1.0.1
Summary: Enterprise-grade vector database library for AI applications with ChromaDB, multi-modal support, and cloud integration
Home-page: https://github.com/albanmaxhuni/ai-prishtina-chromadb-client
Author: Alban Maxhuni, PhD
Author-email: "Alban Maxhuni, PhD" <info@albanmaxhuni.com>
License: AGPL-3.0-or-later OR Commercial
Project-URL: Homepage, https://github.com/albanmaxhuni/ai-prishtina-chromadb-client
Project-URL: Documentation, https://docs.ai-prishtina.com
Project-URL: Repository, https://github.com/albanmaxhuni/ai-prishtina-chromadb-client
Project-URL: Bug Reports, https://github.com/albanmaxhuni/ai-prishtina-chromadb-client/issues
Keywords: vector database,chromadb,embeddings,semantic search,AI,machine learning
Classifier: Development Status :: 5 - Production/Stable
Classifier: Intended Audience :: Developers
Classifier: Intended Audience :: Science/Research
Classifier: License :: OSI Approved :: GNU Affero General Public License v3 or later (AGPLv3+)
Classifier: Operating System :: OS Independent
Classifier: Programming Language :: Python :: 3
Classifier: Programming Language :: Python :: 3.8
Classifier: Programming Language :: Python :: 3.9
Classifier: Programming Language :: Python :: 3.10
Classifier: Programming Language :: Python :: 3.11
Classifier: Programming Language :: Python :: 3.12
Classifier: Topic :: Scientific/Engineering :: Artificial Intelligence
Classifier: Topic :: Database
Classifier: Topic :: Software Development :: Libraries :: Python Modules
Requires-Python: >=3.8
License-File: LICENSE
Requires-Dist: chromadb>=0.4.0
Requires-Dist: numpy>=1.21.0
Requires-Dist: pandas>=2.0.0
Requires-Dist: scikit-learn>=1.0.0
Requires-Dist: sentence-transformers>=2.2.2
Requires-Dist: pydantic<2.0.0,>=1.10.0
Requires-Dist: python-dotenv>=0.19.0
Requires-Dist: requests>=2.26.0
Requires-Dist: tqdm>=4.65.0
Requires-Dist: aiofiles>=23.1.0
Requires-Dist: aiohttp>=3.8.0
Requires-Dist: openpyxl>=3.0.0
Requires-Dist: python-docx>=0.8.11
Requires-Dist: pypdf>=3.0.0
Requires-Dist: Pillow>=8.0.0
Requires-Dist: psutil>=5.9.0
Requires-Dist: websockets>=11.0.0
Requires-Dist: cryptography>=41.0.0
Requires-Dist: bcrypt>=4.0.0
Requires-Dist: PyJWT>=2.8.0
Provides-Extra: full
Requires-Dist: torch>=1.9.0; extra == "full"
Requires-Dist: transformers>=4.11.0; extra == "full"
Requires-Dist: opencv-python>=4.10.0; extra == "full"
Requires-Dist: boto3>=1.26.0; extra == "full"
Requires-Dist: google-cloud-storage>=2.0.0; extra == "full"
Requires-Dist: azure-storage-blob>=12.0.0; extra == "full"
Requires-Dist: minio>=7.2.0; extra == "full"
Requires-Dist: redis>=4.0.0; extra == "full"
Requires-Dist: soundfile>=0.13.1; extra == "full"
Requires-Dist: docker>=6.0.0; extra == "full"
Provides-Extra: cloud
Requires-Dist: boto3>=1.26.0; extra == "cloud"
Requires-Dist: google-cloud-storage>=2.0.0; extra == "cloud"
Requires-Dist: azure-storage-blob>=12.0.0; extra == "cloud"
Requires-Dist: minio>=7.2.0; extra == "cloud"
Provides-Extra: ml
Requires-Dist: torch>=1.9.0; extra == "ml"
Requires-Dist: transformers>=4.11.0; extra == "ml"
Requires-Dist: opencv-python>=4.10.0; extra == "ml"
Requires-Dist: soundfile>=0.13.1; extra == "ml"
Requires-Dist: librosa>=0.10.0; extra == "ml"
Requires-Dist: matplotlib>=3.6.0; extra == "ml"
Requires-Dist: seaborn>=0.12.0; extra == "ml"
Provides-Extra: dev
Requires-Dist: pytest>=7.0.0; extra == "dev"
Requires-Dist: pytest-asyncio>=0.21.0; extra == "dev"
Requires-Dist: pytest-cov>=4.1.0; extra == "dev"
Requires-Dist: pytest-mock>=3.10.0; extra == "dev"
Requires-Dist: black>=23.0.0; extra == "dev"
Requires-Dist: isort>=5.0.0; extra == "dev"
Requires-Dist: flake8>=6.0.0; extra == "dev"
Requires-Dist: mypy>=1.0.0; extra == "dev"
Provides-Extra: docs
Requires-Dist: sphinx>=7.0.0; extra == "docs"
Requires-Dist: sphinx-rtd-theme>=1.3.0; extra == "docs"
Requires-Dist: myst-parser>=2.0.0; extra == "docs"
Dynamic: author
Dynamic: home-page
Dynamic: license-file
Dynamic: requires-python
